<?xml version="1.0" encoding="ISO-8859-1"?>
<document name="PaySlip_TimesNewRoman_13_1b-f_6.tif" type="PaySlip" font="TimesNewRoman" font_size="13" noise="true">
  <fraud value="A" x="1174" y="1107" width="33" height="37"/>
  <fraud value="s" x="1211" y="1119" width="16" height="25"/>
  <fraud value="s" x="1232" y="1119" width="16" height="25"/>
  <fraud value="u" x="1250" y="1119" width="26" height="25"/>
  <fraud value="r" x="1278" y="1119" width="17" height="24"/>
  <fraud value="a" x="1297" y="1118" width="22" height="26"/>
  <fraud value="n" x="1320" y="1119" width="26" height="24"/>
  <fraud value="c" x="1349" y="1118" width="20" height="26"/>
  <fraud value="e" x="1373" y="1119" width="17" height="25"/>
  <fraud value="2" x="1994" y="3071" width="22" height="36"/>
  <fraud value="2" x="2020" y="3071" width="23" height="36"/>
</document>